tonic_api/__init__.py
tonic_api/api.py
tonic_api/classes/__init__.py
tonic_api/classes/httpclient.py
tonic_api/classes/model.py
tonic_api/classes/trained_model.py
tonic_api/classes/training_job_status.py
tonic_api/classes/workspace.py
tonic_api/services/__init__.py
tonic_api/services/models.py
tonic_api/services/workspaces.py
tonic_api-2.1.4.dist-info/WHEEL
tonic_api-2.1.4.dist-info/METADATA
tonic_api-2.1.4.dist-info/RECORD
